[
  {
    "FL_DATE": "2017-01-01T00:00:00",
    "ORIGIN": "OGG",
    "DEST": "LAX",
    "CRS_DEP_TIME": 2136,
    "CRS_ARR_TIME": 459,
    "ARR_DELAY": -36.0,
    "CRS_ELAPSED_TIME": 323.0,
    "DISTANCE": 2486.0
  },
  {
    "FL_DATE": "2017-01-01T00:00:00",
    "ORIGIN": "OGG",
    "DEST": "LAX",
    "CRS_DEP_TIME": 1355,
    "CRS_ARR_TIME": 2127,
    "ARR_DELAY": 2.0,
    "CRS_ELAPSED_TIME": 332.0,
    "DISTANCE": 2486.0
  },
  {
    "FL_DATE": "2017-01-01T00:00:00",
    "ORIGIN": "OGG",
    "DEST": "LAX",
    "CRS_DEP_TIME": 2326,
    "CRS_ARR_TIME": 653,
    "ARR_DELAY": -9.0,
    "CRS_ELAPSED_TIME": 327.0,
    "DISTANCE": 2486.0
  },
  {
    "FL_DATE": "2017-01-01T00:00:00",
    "ORIGIN": "OGG",
    "DEST": "LAX",
    "CRS_DEP_TIME": 1440,
    "CRS_ARR_TIME": 2135,
    "ARR_DELAY": 44.0,
    "CRS_ELAPSED_TIME": 295.0,
    "DISTANCE": 2486.0
  },
  {
    "FL_DATE": "2017-01-01T00:00:00",
    "ORIGIN": "OGG",
    "DEST": "LAX",
    "CRS_DEP_TIME": 1400,
    "CRS_ARR_TIME": 2133,
    "ARR_DELAY": 7.0,
    "CRS_ELAPSED_TIME": 333.0,
    "DISTANCE": 2486.0
  },
  {
    "FL_DATE": "2017-01-01T00:00:00",
    "ORIGIN": "OGG",
    "DEST": "LAX",
    "CRS_DEP_TIME": 2310,
    "CRS_ARR_TIME": 639,
    "ARR_DELAY": -20.0,
    "CRS_ELAPSED_TIME": 329.0,
    "DISTANCE": 2486.0
  },
  {
    "FL_DATE": "2017-01-01T00:00:00",
    "ORIGIN": "OGG",
    "DEST": "LAX",
    "CRS_DEP_TIME": 2140,
    "CRS_ARR_TIME": 449,
    "ARR_DELAY": -22.0,
    "CRS_ELAPSED_TIME": 309.0,
    "DISTANCE": 2486.0
  },
  {
    "FL_DATE": "2017-01-01T00:00:00",
    "ORIGIN": "OGG",
    "DEST": "LAX",
    "CRS_DEP_TIME": 1515,
    "CRS_ARR_TIME": 2230,
    "ARR_DELAY": 8.0,
    "CRS_ELAPSED_TIME": 315.0,
    "DISTANCE": 2486.0
  },
  {
    "FL_DATE": "2017-01-01T00:00:00",
    "ORIGIN": "OGG",
    "DEST": "LAX",
    "CRS_DEP_TIME": 2313,
    "CRS_ARR_TIME": 630,
    "ARR_DELAY": 9.0,
    "CRS_ELAPSED_TIME": 317.0,
    "DISTANCE": 2486.0
  },
  {
    "FL_DATE": "2017-01-01T00:00:00",
    "ORIGIN": "OGG",
    "DEST": "LAX",
    "CRS_DEP_TIME": 1527,
    "CRS_ARR_TIME": 2250,
    "ARR_DELAY": 181.0,
    "CRS_ELAPSED_TIME": 323.0,
    "DISTANCE": 2486.0
  },
  {
    "FL_DATE": "2017-01-01T00:00:00",
    "ORIGIN": "OGG",
    "DEST": "LAX",
    "CRS_DEP_TIME": 2350,
    "CRS_ARR_TIME": 707,
    "ARR_DELAY": -5.0,
    "CRS_ELAPSED_TIME": 317.0,
    "DISTANCE": 2486.0
  },
  {
    "FL_DATE": "2017-01-01T00:00:00",
    "ORIGIN": "OGG",
    "DEST": "LAX",
    "CRS_DEP_TIME": 1355,
    "CRS_ARR_TIME": 2118,
    "ARR_DELAY": -23.0,
    "CRS_ELAPSED_TIME": 323.0,
    "DISTANCE": 2486.0
  },
  {
    "FL_DATE": "2017-01-02T00:00:00",
    "ORIGIN": "OGG",
    "DEST": "LAX",
    "CRS_DEP_TIME": 1515,
    "CRS_ARR_TIME": 2230,
    "ARR_DELAY": 44.0,
    "CRS_ELAPSED_TIME": 315.0,
    "DISTANCE": 2486.0
  },
  {
    "FL_DATE": "2017-01-02T00:00:00",
    "ORIGIN": "OGG",
    "DEST": "LAX",
    "CRS_DEP_TIME": 2313,
    "CRS_ARR_TIME": 630,
    "ARR_DELAY": 2.0,
    "CRS_ELAPSED_TIME": 317.0,
    "DISTANCE": 2486.0
  },
  {
    "FL_DATE": "2017-01-02T00:00:00",
    "ORIGIN": "OGG",
    "DEST": "LAX",
    "CRS_DEP_TIME": 1527,
    "CRS_ARR_TIME": 2250,
    "ARR_DELAY": 19.0,
    "CRS_ELAPSED_TIME": 323.0,
    "DISTANCE": 2486.0
  },
  {
    "FL_DATE": "2017-01-02T00:00:00",
    "ORIGIN": "OGG",
    "DEST": "LAX",
    "CRS_DEP_TIME": 2350,
    "CRS_ARR_TIME": 707,
    "ARR_DELAY": 15.0,
    "CRS_ELAPSED_TIME": 317.0,
    "DISTANCE": 2486.0
  },
  {
    "FL_DATE": "2017-01-02T00:00:00",
    "ORIGIN": "OGG",
    "DEST": "LAX",
    "CRS_DEP_TIME": 1355,
    "CRS_ARR_TIME": 2118,
    "ARR_DELAY": -18.0,
    "CRS_ELAPSED_TIME": 323.0,
    "DISTANCE": 2486.0
  },
  {
    "FL_DATE": "2017-01-02T00:00:00",
    "ORIGIN": "OGG",
    "DEST": "LAX",
    "CRS_DEP_TIME": 1440,
    "CRS_ARR_TIME": 2135,
    "ARR_DELAY": 91.0,
    "CRS_ELAPSED_TIME": 295.0,
    "DISTANCE": 2486.0
  },
  {
    "FL_DATE": "2017-01-02T00:00:00",
    "ORIGIN": "OGG",
    "DEST": "LAX",
    "CRS_DEP_TIME": 2330,
    "CRS_ARR_TIME": 625,
    "ARR_DELAY": -17.0,
    "CRS_ELAPSED_TIME": 295.0,
    "DISTANCE": 2486.0
  },
  {
    "FL_DATE": "2017-01-02T00:00:00",
    "ORIGIN": "OGG",
    "DEST": "LAX",
    "CRS_DEP_TIME": 1400,
    "CRS_ARR_TIME": 2133,
    "ARR_DELAY": 16.0,
    "CRS_ELAPSED_TIME": 333.0,
    "DISTANCE": 2486.0
  },
  {
    "FL_DATE": "2017-01-02T00:00:00",
    "ORIGIN": "OGG",
    "DEST": "LAX",
    "CRS_DEP_TIME": 2306,
    "CRS_ARR_TIME": 631,
    "ARR_DELAY": -17.0,
    "CRS_ELAPSED_TIME": 325.0,
    "DISTANCE": 2486.0
  },
  {
    "FL_DATE": "2017-01-02T00:00:00",
    "ORIGIN": "OGG",
    "DEST": "LAX",
    "CRS_DEP_TIME": 2140,
    "CRS_ARR_TIME": 449,
    "ARR_DELAY": -33.0,
    "CRS_ELAPSED_TIME": 309.0,
    "DISTANCE": 2486.0
  },
  {
    "FL_DATE": "2017-01-02T00:00:00",
    "ORIGIN": "OGG",
    "DEST": "LAX",
    "CRS_DEP_TIME": 2136,
    "CRS_ARR_TIME": 500,
    "ARR_DELAY": -44.0,
    "CRS_ELAPSED_TIME": 324.0,
    "DISTANCE": 2486.0
  },
  {
    "FL_DATE": "2017-01-02T00:00:00",
    "ORIGIN": "OGG",
    "DEST": "LAX",
    "CRS_DEP_TIME": 1405,
    "CRS_ARR_TIME": 2140,
    "ARR_DELAY": 70.0,
    "CRS_ELAPSED_TIME": 335.0,
    "DISTANCE": 2486.0
  },
  {
    "FL_DATE": "2017-01-02T00:00:00",
    "ORIGIN": "OGG",
    "DEST": "LAX",
    "CRS_DEP_TIME": 2326,
    "CRS_ARR_TIME": 655,
    "ARR_DELAY": 121.0,
    "CRS_ELAPSED_TIME": 329.0,
    "DISTANCE": 2486.0
  },
  {
    "FL_DATE": "2017-01-03T00:00:00",
    "ORIGIN": "OGG",
    "DEST": "LAX",
    "CRS_DEP_TIME": 1405,
    "CRS_ARR_TIME": 2140,
    "ARR_DELAY": -34.0,
    "CRS_ELAPSED_TIME": 335.0,
    "DISTANCE": 2486.0
  },
  {
    "FL_DATE": "2017-01-03T00:00:00",
    "ORIGIN": "OGG",
    "DEST": "LAX",
    "CRS_DEP_TIME": 2136,
    "CRS_ARR_TIME": 500,
    "ARR_DELAY": -57.0,
    "CRS_ELAPSED_TIME": 324.0,
    "DISTANCE": 2486.0
  },
  {
    "FL_DATE": "2017-01-03T00:00:00",
    "ORIGIN": "OGG",
    "DEST": "LAX",
    "CRS_DEP_TIME": 1440,
    "CRS_ARR_TIME": 2135,
    "ARR_DELAY": 12.0,
    "CRS_ELAPSED_TIME": 295.0,
    "DISTANCE": 2486.0
  },
  {
    "FL_DATE": "2017-01-03T00:00:00",
    "ORIGIN": "OGG",
    "DEST": "LAX",
    "CRS_DEP_TIME": 2330,
    "CRS_ARR_TIME": 625,
    "ARR_DELAY": -20.0,
    "CRS_ELAPSED_TIME": 295.0,
    "DISTANCE": 2486.0
  },
  {
    "FL_DATE": "2017-01-03T00:00:00",
    "ORIGIN": "OGG",
    "DEST": "LAX",
    "CRS_DEP_TIME": 1400,
    "CRS_ARR_TIME": 2133,
    "ARR_DELAY": -13.0,
    "CRS_ELAPSED_TIME": 333.0,
    "DISTANCE": 2486.0
  },
  {
    "FL_DATE": "2017-01-03T00:00:00",
    "ORIGIN": "OGG",
    "DEST": "LAX",
    "CRS_DEP_TIME": 2310,
    "CRS_ARR_TIME": 639,
    "ARR_DELAY": -61.0,
    "CRS_ELAPSED_TIME": 329.0,
    "DISTANCE": 2486.0
  },
  {
    "FL_DATE": "2017-01-03T00:00:00",
    "ORIGIN": "OGG",
    "DEST": "LAX",
    "CRS_DEP_TIME": 2140,
    "CRS_ARR_TIME": 449,
    "ARR_DELAY": -30.0,
    "CRS_ELAPSED_TIME": 309.0,
    "DISTANCE": 2486.0
  },
  {
    "FL_DATE": "2017-01-03T00:00:00",
    "ORIGIN": "OGG",
    "DEST": "LAX",
    "CRS_DEP_TIME": 1515,
    "CRS_ARR_TIME": 2230,
    "ARR_DELAY": 21.0,
    "CRS_ELAPSED_TIME": 315.0,
    "DISTANCE": 2486.0
  },
  {
    "FL_DATE": "2017-01-03T00:00:00",
    "ORIGIN": "OGG",
    "DEST": "LAX",
    "CRS_DEP_TIME": 2313,
    "CRS_ARR_TIME": 630,
    "ARR_DELAY": -49.0,
    "CRS_ELAPSED_TIME": 317.0,
    "DISTANCE": 2486.0
  },
  {
    "FL_DATE": "2017-01-03T00:00:00",
    "ORIGIN": "OGG",
    "DEST": "LAX",
    "CRS_DEP_TIME": 1527,
    "CRS_ARR_TIME": 2250,
    "ARR_DELAY": 76.0,
    "CRS_ELAPSED_TIME": 323.0,
    "DISTANCE": 2486.0
  },
  {
    "FL_DATE": "2017-01-03T00:00:00",
    "ORIGIN": "OGG",
    "DEST": "LAX",
    "CRS_DEP_TIME": 1355,
    "CRS_ARR_TIME": 2118,
    "ARR_DELAY": 10.0,
    "CRS_ELAPSED_TIME": 323.0,
    "DISTANCE": 2486.0
  },
  {
    "FL_DATE": "2017-01-04T00:00:00",
    "ORIGIN": "OGG",
    "DEST": "LAX",
    "CRS_DEP_TIME": 1515,
    "CRS_ARR_TIME": 2230,
    "ARR_DELAY": -3.0,
    "CRS_ELAPSED_TIME": 315.0,
    "DISTANCE": 2486.0
  },
  {
    "FL_DATE": "2017-01-04T00:00:00",
    "ORIGIN": "OGG",
    "DEST": "LAX",
    "CRS_DEP_TIME": 2313,
    "CRS_ARR_TIME": 630,
    "ARR_DELAY": -15.0,
    "CRS_ELAPSED_TIME": 317.0,
    "DISTANCE": 2486.0
  },
  {
    "FL_DATE": "2017-01-04T00:00:00",
    "ORIGIN": "OGG",
    "DEST": "LAX",
    "CRS_DEP_TIME": 1527,
    "CRS_ARR_TIME": 2250,
    "ARR_DELAY": -7.0,
    "CRS_ELAPSED_TIME": 323.0,
    "DISTANCE": 2486.0
  },
  {
    "FL_DATE": "2017-01-04T00:00:00",
    "ORIGIN": "OGG",
    "DEST": "LAX",
    "CRS_DEP_TIME": 1355,
    "CRS_ARR_TIME": 2118,
    "ARR_DELAY": -48.0,
    "CRS_ELAPSED_TIME": 323.0,
    "DISTANCE": 2486.0
  },
  {
    "FL_DATE": "2017-01-04T00:00:00",
    "ORIGIN": "OGG",
    "DEST": "LAX",
    "CRS_DEP_TIME": 1405,
    "CRS_ARR_TIME": 2140,
    "ARR_DELAY": -28.0,
    "CRS_ELAPSED_TIME": 335.0,
    "DISTANCE": 2486.0
  },
  {
    "FL_DATE": "2017-01-04T00:00:00",
    "ORIGIN": "OGG",
    "DEST": "LAX",
    "CRS_DEP_TIME": 2136,
    "CRS_ARR_TIME": 500,
    "ARR_DELAY": -39.0,
    "CRS_ELAPSED_TIME": 324.0,
    "DISTANCE": 2486.0
  },
  {
    "FL_DATE": "2017-01-04T00:00:00",
    "ORIGIN": "OGG",
    "DEST": "LAX",
    "CRS_DEP_TIME": 1440,
    "CRS_ARR_TIME": 2135,
    "ARR_DELAY": -1.0,
    "CRS_ELAPSED_TIME": 295.0,
    "DISTANCE": 2486.0
  },
  {
    "FL_DATE": "2017-01-04T00:00:00",
    "ORIGIN": "OGG",
    "DEST": "LAX",
    "CRS_DEP_TIME": 2330,
    "CRS_ARR_TIME": 625,
    "ARR_DELAY": -33.0,
    "CRS_ELAPSED_TIME": 295.0,
    "DISTANCE": 2486.0
  },
  {
    "FL_DATE": "2017-01-04T00:00:00",
    "ORIGIN": "OGG",
    "DEST": "LAX",
    "CRS_DEP_TIME": 1347,
    "CRS_ARR_TIME": 2114,
    "ARR_DELAY": -35.0,
    "CRS_ELAPSED_TIME": 327.0,
    "DISTANCE": 2486.0
  },
  {
    "FL_DATE": "2017-01-04T00:00:00",
    "ORIGIN": "OGG",
    "DEST": "LAX",
    "CRS_DEP_TIME": 2310,
    "CRS_ARR_TIME": 639,
    "ARR_DELAY": -62.0,
    "CRS_ELAPSED_TIME": 329.0,
    "DISTANCE": 2486.0
  },
  {
    "FL_DATE": "2017-01-05T00:00:00",
    "ORIGIN": "OGG",
    "DEST": "LAX",
    "CRS_DEP_TIME": 1347,
    "CRS_ARR_TIME": 2114,
    "ARR_DELAY": -54.0,
    "CRS_ELAPSED_TIME": 327.0,
    "DISTANCE": 2486.0
  },
  {
    "FL_DATE": "2017-01-05T00:00:00",
    "ORIGIN": "OGG",
    "DEST": "LAX",
    "CRS_DEP_TIME": 2310,
    "CRS_ARR_TIME": 639,
    "ARR_DELAY": -50.0,
    "CRS_ELAPSED_TIME": 329.0,
    "DISTANCE": 2486.0
  },
  {
    "FL_DATE": "2017-01-05T00:00:00",
    "ORIGIN": "OGG",
    "DEST": "LAX",
    "CRS_DEP_TIME": 1355,
    "CRS_ARR_TIME": 2130,
    "ARR_DELAY": -25.0,
    "CRS_ELAPSED_TIME": 335.0,
    "DISTANCE": 2486.0
  },
  {
    "FL_DATE": "2017-01-05T00:00:00",
    "ORIGIN": "OGG",
    "DEST": "LAX",
    "CRS_DEP_TIME": 1440,
    "CRS_ARR_TIME": 2135,
    "ARR_DELAY": 19.0,
    "CRS_ELAPSED_TIME": 295.0,
    "DISTANCE": 2486.0
  },
  {
    "FL_DATE": "2017-01-05T00:00:00",
    "ORIGIN": "OGG",
    "DEST": "LAX",
    "CRS_DEP_TIME": 2330,
    "CRS_ARR_TIME": 625,
    "ARR_DELAY": -25.0,
    "CRS_ELAPSED_TIME": 295.0,
    "DISTANCE": 2486.0
  },
  {
    "FL_DATE": "2017-01-05T00:00:00",
    "ORIGIN": "OGG",
    "DEST": "LAX",
    "CRS_DEP_TIME": 2136,
    "CRS_ARR_TIME": 500,
    "ARR_DELAY": -4.0,
    "CRS_ELAPSED_TIME": 324.0,
    "DISTANCE": 2486.0
  },
  {
    "FL_DATE": "2017-01-05T00:00:00",
    "ORIGIN": "OGG",
    "DEST": "LAX",
    "CRS_DEP_TIME": 1530,
    "CRS_ARR_TIME": 2235,
    "ARR_DELAY": 149.0,
    "CRS_ELAPSED_TIME": 305.0,
    "DISTANCE": 2486.0
  },
  {
    "FL_DATE": "2017-01-05T00:00:00",
    "ORIGIN": "OGG",
    "DEST": "LAX",
    "CRS_DEP_TIME": 2313,
    "CRS_ARR_TIME": 630,
    "ARR_DELAY": 16.0,
    "CRS_ELAPSED_TIME": 317.0,
    "DISTANCE": 2486.0
  },
  {
    "FL_DATE": "2017-01-05T00:00:00",
    "ORIGIN": "OGG",
    "DEST": "LAX",
    "CRS_DEP_TIME": 1527,
    "CRS_ARR_TIME": 2250,
    "ARR_DELAY": 27.0,
    "CRS_ELAPSED_TIME": 323.0,
    "DISTANCE": 2486.0
  },
  {
    "FL_DATE": "2017-01-05T00:00:00",
    "ORIGIN": "OGG",
    "DEST": "LAX",
    "CRS_DEP_TIME": 1355,
    "CRS_ARR_TIME": 2118,
    "ARR_DELAY": -29.0,
    "CRS_ELAPSED_TIME": 323.0,
    "DISTANCE": 2486.0
  },
  {
    "FL_DATE": "2017-01-06T00:00:00",
    "ORIGIN": "OGG",
    "DEST": "LAX",
    "CRS_DEP_TIME": 1405,
    "CRS_ARR_TIME": 2140,
    "ARR_DELAY": 38.0,
    "CRS_ELAPSED_TIME": 335.0,
    "DISTANCE": 2486.0
  },
  {
    "FL_DATE": "2017-01-06T00:00:00",
    "ORIGIN": "OGG",
    "DEST": "LAX",
    "CRS_DEP_TIME": 2136,
    "CRS_ARR_TIME": 500,
    "ARR_DELAY": -33.0,
    "CRS_ELAPSED_TIME": 324.0,
    "DISTANCE": 2486.0
  },
  {
    "FL_DATE": "2017-01-06T00:00:00",
    "ORIGIN": "OGG",
    "DEST": "LAX",
    "CRS_DEP_TIME": 1530,
    "CRS_ARR_TIME": 2235,
    "ARR_DELAY": 15.0,
    "CRS_ELAPSED_TIME": 305.0,
    "DISTANCE": 2486.0
  },
  {
    "FL_DATE": "2017-01-06T00:00:00",
    "ORIGIN": "OGG",
    "DEST": "LAX",
    "CRS_DEP_TIME": 2313,
    "CRS_ARR_TIME": 630,
    "ARR_DELAY": -18.0,
    "CRS_ELAPSED_TIME": 317.0,
    "DISTANCE": 2486.0
  },
  {
    "FL_DATE": "2017-01-06T00:00:00",
    "ORIGIN": "OGG",
    "DEST": "LAX",
    "CRS_DEP_TIME": 1527,
    "CRS_ARR_TIME": 2250,
    "ARR_DELAY": 18.0,
    "CRS_ELAPSED_TIME": 323.0,
    "DISTANCE": 2486.0
  },
  {
    "FL_DATE": "2017-01-06T00:00:00",
    "ORIGIN": "OGG",
    "DEST": "LAX",
    "CRS_DEP_TIME": 1355,
    "CRS_ARR_TIME": 2118,
    "ARR_DELAY": 12.0,
    "CRS_ELAPSED_TIME": 323.0,
    "DISTANCE": 2486.0
  },
  {
    "FL_DATE": "2017-01-06T00:00:00",
    "ORIGIN": "OGG",
    "DEST": "LAX",
    "CRS_DEP_TIME": 1440,
    "CRS_ARR_TIME": 2135,
    "ARR_DELAY": -8.0,
    "CRS_ELAPSED_TIME": 295.0,
    "DISTANCE": 2486.0
  },
  {
    "FL_DATE": "2017-01-06T00:00:00",
    "ORIGIN": "OGG",
    "DEST": "LAX",
    "CRS_DEP_TIME": 2330,
    "CRS_ARR_TIME": 625,
    "ARR_DELAY": -25.0,
    "CRS_ELAPSED_TIME": 295.0,
    "DISTANCE": 2486.0
  },
  {
    "FL_DATE": "2017-01-06T00:00:00",
    "ORIGIN": "OGG",
    "DEST": "LAX",
    "CRS_DEP_TIME": 1347,
    "CRS_ARR_TIME": 2114,
    "ARR_DELAY": 15.0,
    "CRS_ELAPSED_TIME": 327.0,
    "DISTANCE": 2486.0
  },
  {
    "FL_DATE": "2017-01-06T00:00:00",
    "ORIGIN": "OGG",
    "DEST": "LAX",
    "CRS_DEP_TIME": 2310,
    "CRS_ARR_TIME": 639,
    "ARR_DELAY": 126.0,
    "CRS_ELAPSED_TIME": 329.0,
    "DISTANCE": 2486.0
  },
  {
    "FL_DATE": "2017-01-07T00:00:00",
    "ORIGIN": "OGG",
    "DEST": "LAX",
    "CRS_DEP_TIME": 1347,
    "CRS_ARR_TIME": 2114,
    "ARR_DELAY": -28.0,
    "CRS_ELAPSED_TIME": 327.0,
    "DISTANCE": 2486.0
  },
  {
    "FL_DATE": "2017-01-07T00:00:00",
    "ORIGIN": "OGG",
    "DEST": "LAX",
    "CRS_DEP_TIME": 2310,
    "CRS_ARR_TIME": 639,
    "ARR_DELAY": -44.0,
    "CRS_ELAPSED_TIME": 329.0,
    "DISTANCE": 2486.0
  },
  {
    "FL_DATE": "2017-01-07T00:00:00",
    "ORIGIN": "OGG",
    "DEST": "LAX",
    "CRS_DEP_TIME": 1440,
    "CRS_ARR_TIME": 2135,
    "ARR_DELAY": 43.0,
    "CRS_ELAPSED_TIME": 295.0,
    "DISTANCE": 2486.0
  },
  {
    "FL_DATE": "2017-01-07T00:00:00",
    "ORIGIN": "OGG",
    "DEST": "LAX",
    "CRS_DEP_TIME": 2330,
    "CRS_ARR_TIME": 625,
    "ARR_DELAY": 40.0,
    "CRS_ELAPSED_TIME": 295.0,
    "DISTANCE": 2486.0
  },
  {
    "FL_DATE": "2017-01-07T00:00:00",
    "ORIGIN": "OGG",
    "DEST": "LAX",
    "CRS_DEP_TIME": 1351,
    "CRS_ARR_TIME": 2118,
    "ARR_DELAY": -21.0,
    "CRS_ELAPSED_TIME": 327.0,
    "DISTANCE": 2486.0
  },
  {
    "FL_DATE": "2017-01-07T00:00:00",
    "ORIGIN": "OGG",
    "DEST": "LAX",
    "CRS_DEP_TIME": 2147,
    "CRS_ARR_TIME": 503,
    "ARR_DELAY": -9.0,
    "CRS_ELAPSED_TIME": 316.0,
    "DISTANCE": 2486.0
  },
  {
    "FL_DATE": "2017-01-07T00:00:00",
    "ORIGIN": "OGG",
    "DEST": "LAX",
    "CRS_DEP_TIME": 1530,
    "CRS_ARR_TIME": 2235,
    "ARR_DELAY": -1.0,
    "CRS_ELAPSED_TIME": 305.0,
    "DISTANCE": 2486.0
  },
  {
    "FL_DATE": "2017-01-07T00:00:00",
    "ORIGIN": "OGG",
    "DEST": "LAX",
    "CRS_DEP_TIME": 2313,
    "CRS_ARR_TIME": 630,
    "ARR_DELAY": -38.0,
    "CRS_ELAPSED_TIME": 317.0,
    "DISTANCE": 2486.0
  },
  {
    "FL_DATE": "2017-01-07T00:00:00",
    "ORIGIN": "OGG",
    "DEST": "LAX",
    "CRS_DEP_TIME": 1527,
    "CRS_ARR_TIME": 2250,
    "ARR_DELAY": 21.0,
    "CRS_ELAPSED_TIME": 323.0,
    "DISTANCE": 2486.0
  },
  {
    "FL_DATE": "2017-01-07T00:00:00",
    "ORIGIN": "OGG",
    "DEST": "LAX",
    "CRS_DEP_TIME": 1355,
    "CRS_ARR_TIME": 2118,
    "ARR_DELAY": -22.0,
    "CRS_ELAPSED_TIME": 323.0,
    "DISTANCE": 2486.0
  },
  {
    "FL_DATE": "2017-01-08T00:00:00",
    "ORIGIN": "OGG",
    "DEST": "LAX",
    "CRS_DEP_TIME": 1530,
    "CRS_ARR_TIME": 2235,
    "ARR_DELAY": 14.0,
    "CRS_ELAPSED_TIME": 305.0,
    "DISTANCE": 2486.0
  },
  {
    "FL_DATE": "2017-01-08T00:00:00",
    "ORIGIN": "OGG",
    "DEST": "LAX",
    "CRS_DEP_TIME": 2313,
    "CRS_ARR_TIME": 630,
    "ARR_DELAY": -10.0,
    "CRS_ELAPSED_TIME": 317.0,
    "DISTANCE": 2486.0
  },
  {
    "FL_DATE": "2017-01-08T00:00:00",
    "ORIGIN": "OGG",
    "DEST": "LAX",
    "CRS_DEP_TIME": 1527,
    "CRS_ARR_TIME": 2250,
    "ARR_DELAY": 21.0,
    "CRS_ELAPSED_TIME": 323.0,
    "DISTANCE": 2486.0
  },
  {
    "FL_DATE": "2017-01-08T00:00:00",
    "ORIGIN": "OGG",
    "DEST": "LAX",
    "CRS_DEP_TIME": 1355,
    "CRS_ARR_TIME": 2118,
    "ARR_DELAY": 5.0,
    "CRS_ELAPSED_TIME": 323.0,
    "DISTANCE": 2486.0
  },
  {
    "FL_DATE": "2017-01-08T00:00:00",
    "ORIGIN": "OGG",
    "DEST": "LAX",
    "CRS_DEP_TIME": 1351,
    "CRS_ARR_TIME": 2120,
    "ARR_DELAY": 2.0,
    "CRS_ELAPSED_TIME": 329.0,
    "DISTANCE": 2486.0
  },
  {
    "FL_DATE": "2017-01-08T00:00:00",
    "ORIGIN": "OGG",
    "DEST": "LAX",
    "CRS_DEP_TIME": 2147,
    "CRS_ARR_TIME": 505,
    "ARR_DELAY": -25.0,
    "CRS_ELAPSED_TIME": 318.0,
    "DISTANCE": 2486.0
  },
  {
    "FL_DATE": "2017-01-08T00:00:00",
    "ORIGIN": "OGG",
    "DEST": "LAX",
    "CRS_DEP_TIME": 1440,
    "CRS_ARR_TIME": 2135,
    "ARR_DELAY": 315.0,
    "CRS_ELAPSED_TIME": 295.0,
    "DISTANCE": 2486.0
  },
  {
    "FL_DATE": "2017-01-08T00:00:00",
    "ORIGIN": "OGG",
    "DEST": "LAX",
    "CRS_DEP_TIME": 1349,
    "CRS_ARR_TIME": 2116,
    "ARR_DELAY": 47.0,
    "CRS_ELAPSED_TIME": 327.0,
    "DISTANCE": 2486.0
  },
  {
    "FL_DATE": "2017-01-08T00:00:00",
    "ORIGIN": "OGG",
    "DEST": "LAX",
    "CRS_DEP_TIME": 2310,
    "CRS_ARR_TIME": 639,
    "ARR_DELAY": 1.0,
    "CRS_ELAPSED_TIME": 329.0,
    "DISTANCE": 2486.0
  },
  {
    "FL_DATE": "2017-01-09T00:00:00",
    "ORIGIN": "OGG",
    "DEST": "LAX",
    "CRS_DEP_TIME": 1440,
    "CRS_ARR_TIME": 2135,
    "ARR_DELAY": 8.0,
    "CRS_ELAPSED_TIME": 295.0,
    "DISTANCE": 2486.0
  },
  {
    "FL_DATE": "2017-01-09T00:00:00",
    "ORIGIN": "OGG",
    "DEST": "LAX",
    "CRS_DEP_TIME": 1351,
    "CRS_ARR_TIME": 2120,
    "ARR_DELAY": 200.0,
    "CRS_ELAPSED_TIME": 329.0,
    "DISTANCE": 2486.0
  },
  {
    "FL_DATE": "2017-01-09T00:00:00",
    "ORIGIN": "OGG",
    "DEST": "LAX",
    "CRS_DEP_TIME": 2142,
    "CRS_ARR_TIME": 500,
    "ARR_DELAY": -38.0,
    "CRS_ELAPSED_TIME": 318.0,
    "DISTANCE": 2486.0
  },
  {
    "FL_DATE": "2017-01-09T00:00:00",
    "ORIGIN": "OGG",
    "DEST": "LAX",
    "CRS_DEP_TIME": 1347,
    "CRS_ARR_TIME": 2120,
    "ARR_DELAY": 37.0,
    "CRS_ELAPSED_TIME": 333.0,
    "DISTANCE": 2486.0
  },
  {
    "FL_DATE": "2017-01-09T00:00:00",
    "ORIGIN": "OGG",
    "DEST": "LAX",
    "CRS_DEP_TIME": 2310,
    "CRS_ARR_TIME": 639,
    "ARR_DELAY": -20.0,
    "CRS_ELAPSED_TIME": 329.0,
    "DISTANCE": 2486.0
  },
  {
    "FL_DATE": "2017-01-09T00:00:00",
    "ORIGIN": "OGG",
    "DEST": "LAX",
    "CRS_DEP_TIME": 1530,
    "CRS_ARR_TIME": 2235,
    "ARR_DELAY": 6.0,
    "CRS_ELAPSED_TIME": 305.0,
    "DISTANCE": 2486.0
  },
  {
    "FL_DATE": "2017-01-09T00:00:00",
    "ORIGIN": "OGG",
    "DEST": "LAX",
    "CRS_DEP_TIME": 1413,
    "CRS_ARR_TIME": 2137,
    "ARR_DELAY": 33.0,
    "CRS_ELAPSED_TIME": 324.0,
    "DISTANCE": 2486.0
  },
  {
    "FL_DATE": "2017-01-10T00:00:00",
    "ORIGIN": "OGG",
    "DEST": "LAX",
    "CRS_DEP_TIME": 1413,
    "CRS_ARR_TIME": 2137,
    "ARR_DELAY": -30.0,
    "CRS_ELAPSED_TIME": 324.0,
    "DISTANCE": 2486.0
  },
  {
    "FL_DATE": "2017-01-10T00:00:00",
    "ORIGIN": "OGG",
    "DEST": "LAX",
    "CRS_DEP_TIME": 1351,
    "CRS_ARR_TIME": 2120,
    "ARR_DELAY": -31.0,
    "CRS_ELAPSED_TIME": 329.0,
    "DISTANCE": 2486.0
  },
  {
    "FL_DATE": "2017-01-10T00:00:00",
    "ORIGIN": "OGG",
    "DEST": "LAX",
    "CRS_DEP_TIME": 2142,
    "CRS_ARR_TIME": 500,
    "ARR_DELAY": -34.0,
    "CRS_ELAPSED_TIME": 318.0,
    "DISTANCE": 2486.0
  },
  {
    "FL_DATE": "2017-01-10T00:00:00",
    "ORIGIN": "OGG",
    "DEST": "LAX",
    "CRS_DEP_TIME": 1347,
    "CRS_ARR_TIME": 2120,
    "ARR_DELAY": -42.0,
    "CRS_ELAPSED_TIME": 333.0,
    "DISTANCE": 2486.0
  },
  {
    "FL_DATE": "2017-01-10T00:00:00",
    "ORIGIN": "OGG",
    "DEST": "LAX",
    "CRS_DEP_TIME": 2310,
    "CRS_ARR_TIME": 639,
    "ARR_DELAY": -31.0,
    "CRS_ELAPSED_TIME": 329.0,
    "DISTANCE": 2486.0
  },
  {
    "FL_DATE": "2017-01-10T00:00:00",
    "ORIGIN": "OGG",
    "DEST": "LAX",
    "CRS_DEP_TIME": 1440,
    "CRS_ARR_TIME": 2135,
    "ARR_DELAY": -8.0,
    "CRS_ELAPSED_TIME": 295.0,
    "DISTANCE": 2486.0
  },
  {
    "FL_DATE": "2017-01-10T00:00:00",
    "ORIGIN": "OGG",
    "DEST": "LAX",
    "CRS_DEP_TIME": 1530,
    "CRS_ARR_TIME": 2235,
    "ARR_DELAY": -10.0,
    "CRS_ELAPSED_TIME": 305.0,
    "DISTANCE": 2486.0
  },
  {
    "FL_DATE": "2017-01-11T00:00:00",
    "ORIGIN": "OGG",
    "DEST": "LAX",
    "CRS_DEP_TIME": 1351,
    "CRS_ARR_TIME": 2120,
    "ARR_DELAY": -5.0,
    "CRS_ELAPSED_TIME": 329.0,
    "DISTANCE": 2486.0
  },
  {
    "FL_DATE": "2017-01-11T00:00:00",
    "ORIGIN": "OGG",
    "DEST": "LAX",
    "CRS_DEP_TIME": 2142,
    "CRS_ARR_TIME": 500,
    "ARR_DELAY": -19.0,
    "CRS_ELAPSED_TIME": 318.0,
    "DISTANCE": 2486.0
  },
  {
    "FL_DATE": "2017-01-11T00:00:00",
    "ORIGIN": "OGG",
    "DEST": "LAX",
    "CRS_DEP_TIME": 1440,
    "CRS_ARR_TIME": 2135,
    "ARR_DELAY": 9.0,
    "CRS_ELAPSED_TIME": 295.0,
    "DISTANCE": 2486.0
  },
  {
    "FL_DATE": "2017-01-11T00:00:00",
    "ORIGIN": "OGG",
    "DEST": "LAX",
    "CRS_DEP_TIME": 1347,
    "CRS_ARR_TIME": 2120,
    "ARR_DELAY": -14.0,
    "CRS_ELAPSED_TIME": 333.0,
    "DISTANCE": 2486.0
  },
  {
    "FL_DATE": "2017-01-11T00:00:00",
    "ORIGIN": "OGG",
    "DEST": "LAX",
    "CRS_DEP_TIME": 2310,
    "CRS_ARR_TIME": 639,
    "ARR_DELAY": 0.0,
    "CRS_ELAPSED_TIME": 329.0,
    "DISTANCE": 2486.0
  },
  {
    "FL_DATE": "2017-01-11T00:00:00",
    "ORIGIN": "OGG",
    "DEST": "LAX",
    "CRS_DEP_TIME": 1530,
    "CRS_ARR_TIME": 2235,
    "ARR_DELAY": 5.0,
    "CRS_ELAPSED_TIME": 305.0,
    "DISTANCE": 2486.0
  },
  {
    "FL_DATE": "2017-01-11T00:00:00",
    "ORIGIN": "OGG",
    "DEST": "LAX",
    "CRS_DEP_TIME": 1413,
    "CRS_ARR_TIME": 2137,
    "ARR_DELAY": -15.0,
    "CRS_ELAPSED_TIME": 324.0,
    "DISTANCE": 2486.0
  },
  {
    "FL_DATE": "2017-01-12T00:00:00",
    "ORIGIN": "OGG",
    "DEST": "LAX",
    "CRS_DEP_TIME": 1530,
    "CRS_ARR_TIME": 2235,
    "ARR_DELAY": 106.0,
    "CRS_ELAPSED_TIME": 305.0,
    "DISTANCE": 2486.0
  },
  {
    "FL_DATE": "2017-01-12T00:00:00",
    "ORIGIN": "OGG",
    "DEST": "LAX",
    "CRS_DEP_TIME": 1413,
    "CRS_ARR_TIME": 2137,
    "ARR_DELAY": 6.0,
    "CRS_ELAPSED_TIME": 324.0,
    "DISTANCE": 2486.0
  },
  {
    "FL_DATE": "2017-01-12T00:00:00",
    "ORIGIN": "OGG",
    "DEST": "LAX",
    "CRS_DEP_TIME": 1347,
    "CRS_ARR_TIME": 2120,
    "ARR_DELAY": -15.0,
    "CRS_ELAPSED_TIME": 333.0,
    "DISTANCE": 2486.0
  },
  {
    "FL_DATE": "2017-01-12T00:00:00",
    "ORIGIN": "OGG",
    "DEST": "LAX",
    "CRS_DEP_TIME": 2310,
    "CRS_ARR_TIME": 639,
    "ARR_DELAY": -23.0,
    "CRS_ELAPSED_TIME": 329.0,
    "DISTANCE": 2486.0
  },
  {
    "FL_DATE": "2017-01-12T00:00:00",
    "ORIGIN": "OGG",
    "DEST": "LAX",
    "CRS_DEP_TIME": 1440,
    "CRS_ARR_TIME": 2135,
    "ARR_DELAY": 22.0,
    "CRS_ELAPSED_TIME": 295.0,
    "DISTANCE": 2486.0
  },
  {
    "FL_DATE": "2017-01-12T00:00:00",
    "ORIGIN": "OGG",
    "DEST": "LAX",
    "CRS_DEP_TIME": 1351,
    "CRS_ARR_TIME": 2120,
    "ARR_DELAY": -5.0,
    "CRS_ELAPSED_TIME": 329.0,
    "DISTANCE": 2486.0
  },
  {
    "FL_DATE": "2017-01-12T00:00:00",
    "ORIGIN": "OGG",
    "DEST": "LAX",
    "CRS_DEP_TIME": 2142,
    "CRS_ARR_TIME": 500,
    "ARR_DELAY": -16.0,
    "CRS_ELAPSED_TIME": 318.0,
    "DISTANCE": 2486.0
  },
  {
    "FL_DATE": "2017-01-13T00:00:00",
    "ORIGIN": "OGG",
    "DEST": "LAX",
    "CRS_DEP_TIME": 1351,
    "CRS_ARR_TIME": 2120,
    "ARR_DELAY": 35.0,
    "CRS_ELAPSED_TIME": 329.0,
    "DISTANCE": 2486.0
  },
  {
    "FL_DATE": "2017-01-13T00:00:00",
    "ORIGIN": "OGG",
    "DEST": "LAX",
    "CRS_DEP_TIME": 2142,
    "CRS_ARR_TIME": 500,
    "ARR_DELAY": -1.0,
    "CRS_ELAPSED_TIME": 318.0,
    "DISTANCE": 2486.0
  },
  {
    "FL_DATE": "2017-01-13T00:00:00",
    "ORIGIN": "OGG",
    "DEST": "LAX",
    "CRS_DEP_TIME": 1440,
    "CRS_ARR_TIME": 2135,
    "ARR_DELAY": 15.0,
    "CRS_ELAPSED_TIME": 295.0,
    "DISTANCE": 2486.0
  },
  {
    "FL_DATE": "2017-01-13T00:00:00",
    "ORIGIN": "OGG",
    "DEST": "LAX",
    "CRS_DEP_TIME": 1347,
    "CRS_ARR_TIME": 2120,
    "ARR_DELAY": -7.0,
    "CRS_ELAPSED_TIME": 333.0,
    "DISTANCE": 2486.0
  },
  {
    "FL_DATE": "2017-01-13T00:00:00",
    "ORIGIN": "OGG",
    "DEST": "LAX",
    "CRS_DEP_TIME": 2310,
    "CRS_ARR_TIME": 639,
    "ARR_DELAY": -17.0,
    "CRS_ELAPSED_TIME": 329.0,
    "DISTANCE": 2486.0
  },
  {
    "FL_DATE": "2017-01-13T00:00:00",
    "ORIGIN": "OGG",
    "DEST": "LAX",
    "CRS_DEP_TIME": 1530,
    "CRS_ARR_TIME": 2235,
    "ARR_DELAY": 14.0,
    "CRS_ELAPSED_TIME": 305.0,
    "DISTANCE": 2486.0
  },
  {
    "FL_DATE": "2017-01-13T00:00:00",
    "ORIGIN": "OGG",
    "DEST": "LAX",
    "CRS_DEP_TIME": 2319,
    "CRS_ARR_TIME": 637,
    "ARR_DELAY": -6.0,
    "CRS_ELAPSED_TIME": 318.0,
    "DISTANCE": 2486.0
  },
  {
    "FL_DATE": "2017-01-13T00:00:00",
    "ORIGIN": "OGG",
    "DEST": "LAX",
    "CRS_DEP_TIME": 1413,
    "CRS_ARR_TIME": 2137,
    "ARR_DELAY": -6.0,
    "CRS_ELAPSED_TIME": 324.0,
    "DISTANCE": 2486.0
  },
  {
    "FL_DATE": "2017-01-14T00:00:00",
    "ORIGIN": "OGG",
    "DEST": "LAX",
    "CRS_DEP_TIME": 1347,
    "CRS_ARR_TIME": 2120,
    "ARR_DELAY": 5.0,
    "CRS_ELAPSED_TIME": 333.0,
    "DISTANCE": 2486.0
  },
  {
    "FL_DATE": "2017-01-14T00:00:00",
    "ORIGIN": "OGG",
    "DEST": "LAX",
    "CRS_DEP_TIME": 2310,
    "CRS_ARR_TIME": 639,
    "ARR_DELAY": 2.0,
    "CRS_ELAPSED_TIME": 329.0,
    "DISTANCE": 2486.0
  },
  {
    "FL_DATE": "2017-01-14T00:00:00",
    "ORIGIN": "OGG",
    "DEST": "LAX",
    "CRS_DEP_TIME": 1530,
    "CRS_ARR_TIME": 2235,
    "ARR_DELAY": 0.0,
    "CRS_ELAPSED_TIME": 305.0,
    "DISTANCE": 2486.0
  },
  {
    "FL_DATE": "2017-01-14T00:00:00",
    "ORIGIN": "OGG",
    "DEST": "LAX",
    "CRS_DEP_TIME": 2319,
    "CRS_ARR_TIME": 637,
    "ARR_DELAY": -2.0,
    "CRS_ELAPSED_TIME": 318.0,
    "DISTANCE": 2486.0
  },
  {
    "FL_DATE": "2017-01-14T00:00:00",
    "ORIGIN": "OGG",
    "DEST": "LAX",
    "CRS_DEP_TIME": 1413,
    "CRS_ARR_TIME": 2137,
    "ARR_DELAY": -8.0,
    "CRS_ELAPSED_TIME": 324.0,
    "DISTANCE": 2486.0
  },
  {
    "FL_DATE": "2017-01-14T00:00:00",
    "ORIGIN": "OGG",
    "DEST": "LAX",
    "CRS_DEP_TIME": 1353,
    "CRS_ARR_TIME": 2120,
    "ARR_DELAY": 92.0,
    "CRS_ELAPSED_TIME": 327.0,
    "DISTANCE": 2486.0
  },
  {
    "FL_DATE": "2017-01-14T00:00:00",
    "ORIGIN": "OGG",
    "DEST": "LAX",
    "CRS_DEP_TIME": 2147,
    "CRS_ARR_TIME": 503,
    "ARR_DELAY": -1.0,
    "CRS_ELAPSED_TIME": 316.0,
    "DISTANCE": 2486.0
  },
  {
    "FL_DATE": "2017-01-14T00:00:00",
    "ORIGIN": "OGG",
    "DEST": "LAX",
    "CRS_DEP_TIME": 1440,
    "CRS_ARR_TIME": 2135,
    "ARR_DELAY": 11.0,
    "CRS_ELAPSED_TIME": 295.0,
    "DISTANCE": 2486.0
  },
  {
    "FL_DATE": "2017-01-15T00:00:00",
    "ORIGIN": "OGG",
    "DEST": "LAX",
    "CRS_DEP_TIME": 1351,
    "CRS_ARR_TIME": 2118,
    "ARR_DELAY": 21.0,
    "CRS_ELAPSED_TIME": 327.0,
    "DISTANCE": 2486.0
  },
  {
    "FL_DATE": "2017-01-15T00:00:00",
    "ORIGIN": "OGG",
    "DEST": "LAX",
    "CRS_DEP_TIME": 2147,
    "CRS_ARR_TIME": 503,
    "ARR_DELAY": -2.0,
    "CRS_ELAPSED_TIME": 316.0,
    "DISTANCE": 2486.0
  },
  {
    "FL_DATE": "2017-01-15T00:00:00",
    "ORIGIN": "OGG",
    "DEST": "LAX",
    "CRS_DEP_TIME": 1440,
    "CRS_ARR_TIME": 2135,
    "ARR_DELAY": 41.0,
    "CRS_ELAPSED_TIME": 295.0,
    "DISTANCE": 2486.0
  },
  {
    "FL_DATE": "2017-01-15T00:00:00",
    "ORIGIN": "OGG",
    "DEST": "LAX",
    "CRS_DEP_TIME": 1347,
    "CRS_ARR_TIME": 2120,
    "ARR_DELAY": -3.0,
    "CRS_ELAPSED_TIME": 333.0,
    "DISTANCE": 2486.0
  },
  {
    "FL_DATE": "2017-01-15T00:00:00",
    "ORIGIN": "OGG",
    "DEST": "LAX",
    "CRS_DEP_TIME": 2310,
    "CRS_ARR_TIME": 639,
    "ARR_DELAY": -2.0,
    "CRS_ELAPSED_TIME": 329.0,
    "DISTANCE": 2486.0
  },
  {
    "FL_DATE": "2017-01-15T00:00:00",
    "ORIGIN": "OGG",
    "DEST": "LAX",
    "CRS_DEP_TIME": 1530,
    "CRS_ARR_TIME": 2235,
    "ARR_DELAY": 9.0,
    "CRS_ELAPSED_TIME": 305.0,
    "DISTANCE": 2486.0
  },
  {
    "FL_DATE": "2017-01-15T00:00:00",
    "ORIGIN": "OGG",
    "DEST": "LAX",
    "CRS_DEP_TIME": 1413,
    "CRS_ARR_TIME": 2137,
    "ARR_DELAY": -4.0,
    "CRS_ELAPSED_TIME": 324.0,
    "DISTANCE": 2486.0
  },
  {
    "FL_DATE": "2017-01-16T00:00:00",
    "ORIGIN": "OGG",
    "DEST": "LAX",
    "CRS_DEP_TIME": 2142,
    "CRS_ARR_TIME": 500,
    "ARR_DELAY": 8.0,
    "CRS_ELAPSED_TIME": 318.0,
    "DISTANCE": 2486.0
  },
  {
    "FL_DATE": "2017-01-16T00:00:00",
    "ORIGIN": "OGG",
    "DEST": "LAX",
    "CRS_DEP_TIME": 1347,
    "CRS_ARR_TIME": 2120,
    "ARR_DELAY": 3.0,
    "CRS_ELAPSED_TIME": 333.0,
    "DISTANCE": 2486.0
  },
  {
    "FL_DATE": "2017-01-16T00:00:00",
    "ORIGIN": "OGG",
    "DEST": "LAX",
    "CRS_DEP_TIME": 2310,
    "CRS_ARR_TIME": 639,
    "ARR_DELAY": -24.0,
    "CRS_ELAPSED_TIME": 329.0,
    "DISTANCE": 2486.0
  },
  {
    "FL_DATE": "2017-01-16T00:00:00",
    "ORIGIN": "OGG",
    "DEST": "LAX",
    "CRS_DEP_TIME": 1530,
    "CRS_ARR_TIME": 2235,
    "ARR_DELAY": 8.0,
    "CRS_ELAPSED_TIME": 305.0,
    "DISTANCE": 2486.0
  },
  {
    "FL_DATE": "2017-01-16T00:00:00",
    "ORIGIN": "OGG",
    "DEST": "LAX",
    "CRS_DEP_TIME": 1413,
    "CRS_ARR_TIME": 2137,
    "ARR_DELAY": 28.0,
    "CRS_ELAPSED_TIME": 324.0,
    "DISTANCE": 2486.0
  },
  {
    "FL_DATE": "2017-01-16T00:00:00",
    "ORIGIN": "OGG",
    "DEST": "LAX",
    "CRS_DEP_TIME": 1351,
    "CRS_ARR_TIME": 2120,
    "ARR_DELAY": 4.0,
    "CRS_ELAPSED_TIME": 329.0,
    "DISTANCE": 2486.0
  },
  {
    "FL_DATE": "2017-01-16T00:00:00",
    "ORIGIN": "OGG",
    "DEST": "LAX",
    "CRS_DEP_TIME": 1440,
    "CRS_ARR_TIME": 2135,
    "ARR_DELAY": 43.0,
    "CRS_ELAPSED_TIME": 295.0,
    "DISTANCE": 2486.0
  },
  {
    "FL_DATE": "2017-01-17T00:00:00",
    "ORIGIN": "OGG",
    "DEST": "LAX",
    "CRS_DEP_TIME": 1440,
    "CRS_ARR_TIME": 2135,
    "ARR_DELAY": 11.0,
    "CRS_ELAPSED_TIME": 295.0,
    "DISTANCE": 2486.0
  },
  {
    "FL_DATE": "2017-01-17T00:00:00",
    "ORIGIN": "OGG",
    "DEST": "LAX",
    "CRS_DEP_TIME": 2142,
    "CRS_ARR_TIME": 500,
    "ARR_DELAY": -19.0,
    "CRS_ELAPSED_TIME": 318.0,
    "DISTANCE": 2486.0
  },
  {
    "FL_DATE": "2017-01-17T00:00:00",
    "ORIGIN": "OGG",
    "DEST": "LAX",
    "CRS_DEP_TIME": 1347,
    "CRS_ARR_TIME": 2120,
    "ARR_DELAY": 4.0,
    "CRS_ELAPSED_TIME": 333.0,
    "DISTANCE": 2486.0
  },
  {
    "FL_DATE": "2017-01-17T00:00:00",
    "ORIGIN": "OGG",
    "DEST": "LAX",
    "CRS_DEP_TIME": 2310,
    "CRS_ARR_TIME": 639,
    "ARR_DELAY": -17.0,
    "CRS_ELAPSED_TIME": 329.0,
    "DISTANCE": 2486.0
  },
  {
    "FL_DATE": "2017-01-17T00:00:00",
    "ORIGIN": "OGG",
    "DEST": "LAX",
    "CRS_DEP_TIME": 1530,
    "CRS_ARR_TIME": 2235,
    "ARR_DELAY": 1.0,
    "CRS_ELAPSED_TIME": 305.0,
    "DISTANCE": 2486.0
  },
  {
    "FL_DATE": "2017-01-17T00:00:00",
    "ORIGIN": "OGG",
    "DEST": "LAX",
    "CRS_DEP_TIME": 1413,
    "CRS_ARR_TIME": 2137,
    "ARR_DELAY": -11.0,
    "CRS_ELAPSED_TIME": 324.0,
    "DISTANCE": 2486.0
  },
  {
    "FL_DATE": "2017-01-18T00:00:00",
    "ORIGIN": "OGG",
    "DEST": "LAX",
    "CRS_DEP_TIME": 1351,
    "CRS_ARR_TIME": 2120,
    "ARR_DELAY": -23.0,
    "CRS_ELAPSED_TIME": 329.0,
    "DISTANCE": 2486.0
  },
  {
    "FL_DATE": "2017-01-18T00:00:00",
    "ORIGIN": "OGG",
    "DEST": "LAX",
    "CRS_DEP_TIME": 2142,
    "CRS_ARR_TIME": 500,
    "ARR_DELAY": -19.0,
    "CRS_ELAPSED_TIME": 318.0,
    "DISTANCE": 2486.0
  },
  {
    "FL_DATE": "2017-01-18T00:00:00",
    "ORIGIN": "OGG",
    "DEST": "LAX",
    "CRS_DEP_TIME": 2310,
    "CRS_ARR_TIME": 639,
    "ARR_DELAY": 11.0,
    "CRS_ELAPSED_TIME": 329.0,
    "DISTANCE": 2486.0
  },
  {
    "FL_DATE": "2017-01-18T00:00:00",
    "ORIGIN": "OGG",
    "DEST": "LAX",
    "CRS_DEP_TIME": 1530,
    "CRS_ARR_TIME": 2235,
    "ARR_DELAY": -1.0,
    "CRS_ELAPSED_TIME": 305.0,
    "DISTANCE": 2486.0
  },
  {
    "FL_DATE": "2017-01-18T00:00:00",
    "ORIGIN": "OGG",
    "DEST": "LAX",
    "CRS_DEP_TIME": 1413,
    "CRS_ARR_TIME": 2137,
    "ARR_DELAY": -16.0,
    "CRS_ELAPSED_TIME": 324.0,
    "DISTANCE": 2486.0
  },
  {
    "FL_DATE": "2017-01-18T00:00:00",
    "ORIGIN": "OGG",
    "DEST": "LAX",
    "CRS_DEP_TIME": 1440,
    "CRS_ARR_TIME": 2135,
    "ARR_DELAY": 22.0,
    "CRS_ELAPSED_TIME": 295.0,
    "DISTANCE": 2486.0
  },
  {
    "FL_DATE": "2017-01-18T00:00:00",
    "ORIGIN": "OGG",
    "DEST": "LAX",
    "CRS_DEP_TIME": 1347,
    "CRS_ARR_TIME": 2120,
    "ARR_DELAY": -35.0,
    "CRS_ELAPSED_TIME": 333.0,
    "DISTANCE": 2486.0
  },
  {
    "FL_DATE": "2017-01-19T00:00:00",
    "ORIGIN": "OGG",
    "DEST": "LAX",
    "CRS_DEP_TIME": 1351,
    "CRS_ARR_TIME": 2120,
    "ARR_DELAY": -37.0,
    "CRS_ELAPSED_TIME": 329.0,
    "DISTANCE": 2486.0
  },
  {
    "FL_DATE": "2017-01-19T00:00:00",
    "ORIGIN": "OGG",
    "DEST": "LAX",
    "CRS_DEP_TIME": 2142,
    "CRS_ARR_TIME": 500,
    "ARR_DELAY": -30.0,
    "CRS_ELAPSED_TIME": 318.0,
    "DISTANCE": 2486.0
  },
  {
    "FL_DATE": "2017-01-19T00:00:00",
    "ORIGIN": "OGG",
    "DEST": "LAX",
    "CRS_DEP_TIME": 1440,
    "CRS_ARR_TIME": 2135,
    "ARR_DELAY": 0.0,
    "CRS_ELAPSED_TIME": 295.0,
    "DISTANCE": 2486.0
  },
  {
    "FL_DATE": "2017-01-19T00:00:00",
    "ORIGIN": "OGG",
    "DEST": "LAX",
    "CRS_DEP_TIME": 1347,
    "CRS_ARR_TIME": 2120,
    "ARR_DELAY": 97.0,
    "CRS_ELAPSED_TIME": 333.0,
    "DISTANCE": 2486.0
  },
  {
    "FL_DATE": "2017-01-19T00:00:00",
    "ORIGIN": "OGG",
    "DEST": "LAX",
    "CRS_DEP_TIME": 2310,
    "CRS_ARR_TIME": 639,
    "ARR_DELAY": 1.0,
    "CRS_ELAPSED_TIME": 329.0,
    "DISTANCE": 2486.0
  },
  {
    "FL_DATE": "2017-01-19T00:00:00",
    "ORIGIN": "OGG",
    "DEST": "LAX",
    "CRS_DEP_TIME": 1530,
    "CRS_ARR_TIME": 2235,
    "ARR_DELAY": -15.0,
    "CRS_ELAPSED_TIME": 305.0,
    "DISTANCE": 2486.0
  },
  {
    "FL_DATE": "2017-01-19T00:00:00",
    "ORIGIN": "OGG",
    "DEST": "LAX",
    "CRS_DEP_TIME": 1413,
    "CRS_ARR_TIME": 2137,
    "ARR_DELAY": -36.0,
    "CRS_ELAPSED_TIME": 324.0,
    "DISTANCE": 2486.0
  },
  {
    "FL_DATE": "2017-01-20T00:00:00",
    "ORIGIN": "OGG",
    "DEST": "LAX",
    "CRS_DEP_TIME": 1530,
    "CRS_ARR_TIME": 2235,
    "ARR_DELAY": 16.0,
    "CRS_ELAPSED_TIME": 305.0,
    "DISTANCE": 2486.0
  },
  {
    "FL_DATE": "2017-01-20T00:00:00",
    "ORIGIN": "OGG",
    "DEST": "LAX",
    "CRS_DEP_TIME": 2319,
    "CRS_ARR_TIME": 637,
    "ARR_DELAY": -54.0,
    "CRS_ELAPSED_TIME": 318.0,
    "DISTANCE": 2486.0
  },
  {
    "FL_DATE": "2017-01-20T00:00:00",
    "ORIGIN": "OGG",
    "DEST": "LAX",
    "CRS_DEP_TIME": 1413,
    "CRS_ARR_TIME": 2137,
    "ARR_DELAY": -16.0,
    "CRS_ELAPSED_TIME": 324.0,
    "DISTANCE": 2486.0
  },
  {
    "FL_DATE": "2017-01-20T00:00:00",
    "ORIGIN": "OGG",
    "DEST": "LAX",
    "CRS_DEP_TIME": 1440,
    "CRS_ARR_TIME": 2135,
    "ARR_DELAY": -12.0,
    "CRS_ELAPSED_TIME": 295.0,
    "DISTANCE": 2486.0
  },
  {
    "FL_DATE": "2017-01-20T00:00:00",
    "ORIGIN": "OGG",
    "DEST": "LAX",
    "CRS_DEP_TIME": 1347,
    "CRS_ARR_TIME": 2120,
    "ARR_DELAY": -43.0,
    "CRS_ELAPSED_TIME": 333.0,
    "DISTANCE": 2486.0
  },
  {
    "FL_DATE": "2017-01-20T00:00:00",
    "ORIGIN": "OGG",
    "DEST": "LAX",
    "CRS_DEP_TIME": 2310,
    "CRS_ARR_TIME": 639,
    "ARR_DELAY": -45.0,
    "CRS_ELAPSED_TIME": 329.0,
    "DISTANCE": 2486.0
  },
  {
    "FL_DATE": "2017-01-20T00:00:00",
    "ORIGIN": "OGG",
    "DEST": "LAX",
    "CRS_DEP_TIME": 1351,
    "CRS_ARR_TIME": 2120,
    "ARR_DELAY": 13.0,
    "CRS_ELAPSED_TIME": 329.0,
    "DISTANCE": 2486.0
  },
  {
    "FL_DATE": "2017-01-20T00:00:00",
    "ORIGIN": "OGG",
    "DEST": "LAX",
    "CRS_DEP_TIME": 2142,
    "CRS_ARR_TIME": 500,
    "ARR_DELAY": -39.0,
    "CRS_ELAPSED_TIME": 318.0,
    "DISTANCE": 2486.0
  },
  {
    "FL_DATE": "2017-01-21T00:00:00",
    "ORIGIN": "OGG",
    "DEST": "LAX",
    "CRS_DEP_TIME": 1351,
    "CRS_ARR_TIME": 2118,
    "ARR_DELAY": -41.0,
    "CRS_ELAPSED_TIME": 327.0,
    "DISTANCE": 2486.0
  },
  {
    "FL_DATE": "2017-01-21T00:00:00",
    "ORIGIN": "OGG",
    "DEST": "LAX",
    "CRS_DEP_TIME": 2147,
    "CRS_ARR_TIME": 503,
    "ARR_DELAY": -54.0,
    "CRS_ELAPSED_TIME": 316.0,
    "DISTANCE": 2486.0
  },
  {
    "FL_DATE": "2017-01-21T00:00:00",
    "ORIGIN": "OGG",
    "DEST": "LAX",
    "CRS_DEP_TIME": 1440,
    "CRS_ARR_TIME": 2135,
    "ARR_DELAY": -12.0,
    "CRS_ELAPSED_TIME": 295.0,
    "DISTANCE": 2486.0
  },
  {
    "FL_DATE": "2017-01-21T00:00:00",
    "ORIGIN": "OGG",
    "DEST": "LAX",
    "CRS_DEP_TIME": 1347,
    "CRS_ARR_TIME": 2120,
    "ARR_DELAY": -62.0,
    "CRS_ELAPSED_TIME": 333.0,
    "DISTANCE": 2486.0
  },
  {
    "FL_DATE": "2017-01-21T00:00:00",
    "ORIGIN": "OGG",
    "DEST": "LAX",
    "CRS_DEP_TIME": 2310,
    "CRS_ARR_TIME": 639,
    "ARR_DELAY": -71.0,
    "CRS_ELAPSED_TIME": 329.0,
    "DISTANCE": 2486.0
  },
  {
    "FL_DATE": "2017-01-21T00:00:00",
    "ORIGIN": "OGG",
    "DEST": "LAX",
    "CRS_DEP_TIME": 1530,
    "CRS_ARR_TIME": 2235,
    "ARR_DELAY": -10.0,
    "CRS_ELAPSED_TIME": 305.0,
    "DISTANCE": 2486.0
  },
  {
    "FL_DATE": "2017-01-21T00:00:00",
    "ORIGIN": "OGG",
    "DEST": "LAX",
    "CRS_DEP_TIME": 2319,
    "CRS_ARR_TIME": 637,
    "ARR_DELAY": 1022.0,
    "CRS_ELAPSED_TIME": 318.0,
    "DISTANCE": 2486.0
  },
  {
    "FL_DATE": "2017-01-21T00:00:00",
    "ORIGIN": "OGG",
    "DEST": "LAX",
    "CRS_DEP_TIME": 1413,
    "CRS_ARR_TIME": 2137,
    "ARR_DELAY": -54.0,
    "CRS_ELAPSED_TIME": 324.0,
    "DISTANCE": 2486.0
  },
  {
    "FL_DATE": "2017-01-22T00:00:00",
    "ORIGIN": "OGG",
    "DEST": "LAX",
    "CRS_DEP_TIME": 1351,
    "CRS_ARR_TIME": 2120,
    "ARR_DELAY": -14.0,
    "CRS_ELAPSED_TIME": 329.0,
    "DISTANCE": 2486.0
  },
  {
    "FL_DATE": "2017-01-22T00:00:00",
    "ORIGIN": "OGG",
    "DEST": "LAX",
    "CRS_DEP_TIME": 2142,
    "CRS_ARR_TIME": 500,
    "ARR_DELAY": -43.0,
    "CRS_ELAPSED_TIME": 318.0,
    "DISTANCE": 2486.0
  },
  {
    "FL_DATE": "2017-01-22T00:00:00",
    "ORIGIN": "OGG",
    "DEST": "LAX",
    "CRS_DEP_TIME": 1530,
    "CRS_ARR_TIME": 2235,
    "ARR_DELAY": 167.0,
    "CRS_ELAPSED_TIME": 305.0,
    "DISTANCE": 2486.0
  },
  {
    "FL_DATE": "2017-01-22T00:00:00",
    "ORIGIN": "OGG",
    "DEST": "LAX",
    "CRS_DEP_TIME": 1413,
    "CRS_ARR_TIME": 2137,
    "ARR_DELAY": -9.0,
    "CRS_ELAPSED_TIME": 324.0,
    "DISTANCE": 2486.0
  },
  {
    "FL_DATE": "2017-01-22T00:00:00",
    "ORIGIN": "OGG",
    "DEST": "LAX",
    "CRS_DEP_TIME": 1440,
    "CRS_ARR_TIME": 2135,
    "ARR_DELAY": 30.0,
    "CRS_ELAPSED_TIME": 295.0,
    "DISTANCE": 2486.0
  },
  {
    "FL_DATE": "2017-01-22T00:00:00",
    "ORIGIN": "OGG",
    "DEST": "LAX",
    "CRS_DEP_TIME": 1347,
    "CRS_ARR_TIME": 2120,
    "ARR_DELAY": -3.0,
    "CRS_ELAPSED_TIME": 333.0,
    "DISTANCE": 2486.0
  },
  {
    "FL_DATE": "2017-01-22T00:00:00",
    "ORIGIN": "OGG",
    "DEST": "LAX",
    "CRS_DEP_TIME": 2310,
    "CRS_ARR_TIME": 639,
    "ARR_DELAY": -48.0,
    "CRS_ELAPSED_TIME": 329.0,
    "DISTANCE": 2486.0
  },
  {
    "FL_DATE": "2017-01-23T00:00:00",
    "ORIGIN": "OGG",
    "DEST": "LAX",
    "CRS_DEP_TIME": 1347,
    "CRS_ARR_TIME": 2120,
    "ARR_DELAY": -27.0,
    "CRS_ELAPSED_TIME": 333.0,
    "DISTANCE": 2486.0
  },
  {
    "FL_DATE": "2017-01-23T00:00:00",
    "ORIGIN": "OGG",
    "DEST": "LAX",
    "CRS_DEP_TIME": 2310,
    "CRS_ARR_TIME": 639,
    "ARR_DELAY": -24.0,
    "CRS_ELAPSED_TIME": 329.0,
    "DISTANCE": 2486.0
  },
  {
    "FL_DATE": "2017-01-23T00:00:00",
    "ORIGIN": "OGG",
    "DEST": "LAX",
    "CRS_DEP_TIME": 1440,
    "CRS_ARR_TIME": 2135,
    "ARR_DELAY": -2.0,
    "CRS_ELAPSED_TIME": 295.0,
    "DISTANCE": 2486.0
  },
  {
    "FL_DATE": "2017-01-23T00:00:00",
    "ORIGIN": "OGG",
    "DEST": "LAX",
    "CRS_DEP_TIME": 1351,
    "CRS_ARR_TIME": 2120,
    "ARR_DELAY": -28.0,
    "CRS_ELAPSED_TIME": 329.0,
    "DISTANCE": 2486.0
  },
  {
    "FL_DATE": "2017-01-23T00:00:00",
    "ORIGIN": "OGG",
    "DEST": "LAX",
    "CRS_DEP_TIME": 2142,
    "CRS_ARR_TIME": 500,
    "ARR_DELAY": -32.0,
    "CRS_ELAPSED_TIME": 318.0,
    "DISTANCE": 2486.0
  },
  {
    "FL_DATE": "2017-01-23T00:00:00",
    "ORIGIN": "OGG",
    "DEST": "LAX",
    "CRS_DEP_TIME": 1530,
    "CRS_ARR_TIME": 2235,
    "ARR_DELAY": 119.0,
    "CRS_ELAPSED_TIME": 305.0,
    "DISTANCE": 2486.0
  },
  {
    "FL_DATE": "2017-01-23T00:00:00",
    "ORIGIN": "OGG",
    "DEST": "LAX",
    "CRS_DEP_TIME": 1413,
    "CRS_ARR_TIME": 2137,
    "ARR_DELAY": -32.0,
    "CRS_ELAPSED_TIME": 324.0,
    "DISTANCE": 2486.0
  },
  {
    "FL_DATE": "2017-01-24T00:00:00",
    "ORIGIN": "OGG",
    "DEST": "LAX",
    "CRS_DEP_TIME": 1530,
    "CRS_ARR_TIME": 2235,
    "ARR_DELAY": 0.0,
    "CRS_ELAPSED_TIME": 305.0,
    "DISTANCE": 2486.0
  },
  {
    "FL_DATE": "2017-01-24T00:00:00",
    "ORIGIN": "OGG",
    "DEST": "LAX",
    "CRS_DEP_TIME": 1413,
    "CRS_ARR_TIME": 2137,
    "ARR_DELAY": 1.0,
    "CRS_ELAPSED_TIME": 324.0,
    "DISTANCE": 2486.0
  },
  {
    "FL_DATE": "2017-01-24T00:00:00",
    "ORIGIN": "OGG",
    "DEST": "LAX",
    "CRS_DEP_TIME": 1440,
    "CRS_ARR_TIME": 2135,
    "ARR_DELAY": -9.0,
    "CRS_ELAPSED_TIME": 295.0,
    "DISTANCE": 2486.0
  },
  {
    "FL_DATE": "2017-01-24T00:00:00",
    "ORIGIN": "OGG",
    "DEST": "LAX",
    "CRS_DEP_TIME": 2142,
    "CRS_ARR_TIME": 500,
    "ARR_DELAY": -23.0,
    "CRS_ELAPSED_TIME": 318.0,
    "DISTANCE": 2486.0
  },
  {
    "FL_DATE": "2017-01-24T00:00:00",
    "ORIGIN": "OGG",
    "DEST": "LAX",
    "CRS_DEP_TIME": 1347,
    "CRS_ARR_TIME": 2120,
    "ARR_DELAY": -40.0,
    "CRS_ELAPSED_TIME": 333.0,
    "DISTANCE": 2486.0
  },
  {
    "FL_DATE": "2017-01-24T00:00:00",
    "ORIGIN": "OGG",
    "DEST": "LAX",
    "CRS_DEP_TIME": 2310,
    "CRS_ARR_TIME": 639,
    "ARR_DELAY": -49.0,
    "CRS_ELAPSED_TIME": 329.0,
    "DISTANCE": 2486.0
  },
  {
    "FL_DATE": "2017-01-25T00:00:00",
    "ORIGIN": "OGG",
    "DEST": "LAX",
    "CRS_DEP_TIME": 1351,
    "CRS_ARR_TIME": 2120,
    "ARR_DELAY": -18.0,
    "CRS_ELAPSED_TIME": 329.0,
    "DISTANCE": 2486.0
  },
  {
    "FL_DATE": "2017-01-25T00:00:00",
    "ORIGIN": "OGG",
    "DEST": "LAX",
    "CRS_DEP_TIME": 2142,
    "CRS_ARR_TIME": 500,
    "ARR_DELAY": -17.0,
    "CRS_ELAPSED_TIME": 318.0,
    "DISTANCE": 2486.0
  },
  {
    "FL_DATE": "2017-01-25T00:00:00",
    "ORIGIN": "OGG",
    "DEST": "LAX",
    "CRS_DEP_TIME": 1347,
    "CRS_ARR_TIME": 2120,
    "ARR_DELAY": -34.0,
    "CRS_ELAPSED_TIME": 333.0,
    "DISTANCE": 2486.0
  },
  {
    "FL_DATE": "2017-01-25T00:00:00",
    "ORIGIN": "OGG",
    "DEST": "LAX",
    "CRS_DEP_TIME": 2310,
    "CRS_ARR_TIME": 639,
    "ARR_DELAY": -30.0,
    "CRS_ELAPSED_TIME": 329.0,
    "DISTANCE": 2486.0
  },
  {
    "FL_DATE": "2017-01-25T00:00:00",
    "ORIGIN": "OGG",
    "DEST": "LAX",
    "CRS_DEP_TIME": 1440,
    "CRS_ARR_TIME": 2135,
    "ARR_DELAY": 1.0,
    "CRS_ELAPSED_TIME": 295.0,
    "DISTANCE": 2486.0
  },
  {
    "FL_DATE": "2017-01-25T00:00:00",
    "ORIGIN": "OGG",
    "DEST": "LAX",
    "CRS_DEP_TIME": 1530,
    "CRS_ARR_TIME": 2235,
    "ARR_DELAY": -4.0,
    "CRS_ELAPSED_TIME": 305.0,
    "DISTANCE": 2486.0
  },
  {
    "FL_DATE": "2017-01-25T00:00:00",
    "ORIGIN": "OGG",
    "DEST": "LAX",
    "CRS_DEP_TIME": 1413,
    "CRS_ARR_TIME": 2137,
    "ARR_DELAY": -19.0,
    "CRS_ELAPSED_TIME": 324.0,
    "DISTANCE": 2486.0
  },
  {
    "FL_DATE": "2017-01-26T00:00:00",
    "ORIGIN": "OGG",
    "DEST": "LAX",
    "CRS_DEP_TIME": 1530,
    "CRS_ARR_TIME": 2235,
    "ARR_DELAY": 47.0,
    "CRS_ELAPSED_TIME": 305.0,
    "DISTANCE": 2486.0
  },
  {
    "FL_DATE": "2017-01-26T00:00:00",
    "ORIGIN": "OGG",
    "DEST": "LAX",
    "CRS_DEP_TIME": 1413,
    "CRS_ARR_TIME": 2137,
    "ARR_DELAY": 2.0,
    "CRS_ELAPSED_TIME": 324.0,
    "DISTANCE": 2486.0
  },
  {
    "FL_DATE": "2017-01-26T00:00:00",
    "ORIGIN": "OGG",
    "DEST": "LAX",
    "CRS_DEP_TIME": 1440,
    "CRS_ARR_TIME": 2135,
    "ARR_DELAY": 27.0,
    "CRS_ELAPSED_TIME": 295.0,
    "DISTANCE": 2486.0
  },
  {
    "FL_DATE": "2017-01-26T00:00:00",
    "ORIGIN": "OGG",
    "DEST": "LAX",
    "CRS_DEP_TIME": 1351,
    "CRS_ARR_TIME": 2120,
    "ARR_DELAY": -16.0,
    "CRS_ELAPSED_TIME": 329.0,
    "DISTANCE": 2486.0
  },
  {
    "FL_DATE": "2017-01-26T00:00:00",
    "ORIGIN": "OGG",
    "DEST": "LAX",
    "CRS_DEP_TIME": 2142,
    "CRS_ARR_TIME": 500,
    "ARR_DELAY": -6.0,
    "CRS_ELAPSED_TIME": 318.0,
    "DISTANCE": 2486.0
  },
  {
    "FL_DATE": "2017-01-26T00:00:00",
    "ORIGIN": "OGG",
    "DEST": "LAX",
    "CRS_DEP_TIME": 1347,
    "CRS_ARR_TIME": 2120,
    "ARR_DELAY": -23.0,
    "CRS_ELAPSED_TIME": 333.0,
    "DISTANCE": 2486.0
  },
  {
    "FL_DATE": "2017-01-26T00:00:00",
    "ORIGIN": "OGG",
    "DEST": "LAX",
    "CRS_DEP_TIME": 2310,
    "CRS_ARR_TIME": 639,
    "ARR_DELAY": -26.0,
    "CRS_ELAPSED_TIME": 329.0,
    "DISTANCE": 2486.0
  },
  {
    "FL_DATE": "2017-01-27T00:00:00",
    "ORIGIN": "OGG",
    "DEST": "LAX",
    "CRS_DEP_TIME": 1351,
    "CRS_ARR_TIME": 2120,
    "ARR_DELAY": -18.0,
    "CRS_ELAPSED_TIME": 329.0,
    "DISTANCE": 2486.0
  },
  {
    "FL_DATE": "2017-01-27T00:00:00",
    "ORIGIN": "OGG",
    "DEST": "LAX",
    "CRS_DEP_TIME": 2142,
    "CRS_ARR_TIME": 500,
    "ARR_DELAY": -14.0,
    "CRS_ELAPSED_TIME": 318.0,
    "DISTANCE": 2486.0
  },
  {
    "FL_DATE": "2017-01-27T00:00:00",
    "ORIGIN": "OGG",
    "DEST": "LAX",
    "CRS_DEP_TIME": 1440,
    "CRS_ARR_TIME": 2135,
    "ARR_DELAY": 10.0,
    "CRS_ELAPSED_TIME": 295.0,
    "DISTANCE": 2486.0
  },
  {
    "FL_DATE": "2017-01-27T00:00:00",
    "ORIGIN": "OGG",
    "DEST": "LAX",
    "CRS_DEP_TIME": 1347,
    "CRS_ARR_TIME": 2120,
    "ARR_DELAY": -5.0,
    "CRS_ELAPSED_TIME": 333.0,
    "DISTANCE": 2486.0
  },
  {
    "FL_DATE": "2017-01-27T00:00:00",
    "ORIGIN": "OGG",
    "DEST": "LAX",
    "CRS_DEP_TIME": 2310,
    "CRS_ARR_TIME": 639,
    "ARR_DELAY": -9.0,
    "CRS_ELAPSED_TIME": 329.0,
    "DISTANCE": 2486.0
  },
  {
    "FL_DATE": "2017-01-27T00:00:00",
    "ORIGIN": "OGG",
    "DEST": "LAX",
    "CRS_DEP_TIME": 1530,
    "CRS_ARR_TIME": 2235,
    "ARR_DELAY": 9.0,
    "CRS_ELAPSED_TIME": 305.0,
    "DISTANCE": 2486.0
  },
  {
    "FL_DATE": "2017-01-27T00:00:00",
    "ORIGIN": "OGG",
    "DEST": "LAX",
    "CRS_DEP_TIME": 2319,
    "CRS_ARR_TIME": 637,
    "ARR_DELAY": -21.0,
    "CRS_ELAPSED_TIME": 318.0,
    "DISTANCE": 2486.0
  },
  {
    "FL_DATE": "2017-01-27T00:00:00",
    "ORIGIN": "OGG",
    "DEST": "LAX",
    "CRS_DEP_TIME": 1413,
    "CRS_ARR_TIME": 2137,
    "ARR_DELAY": -5.0,
    "CRS_ELAPSED_TIME": 324.0,
    "DISTANCE": 2486.0
  },
  {
    "FL_DATE": "2017-01-28T00:00:00",
    "ORIGIN": "OGG",
    "DEST": "LAX",
    "CRS_DEP_TIME": 1530,
    "CRS_ARR_TIME": 2235,
    "ARR_DELAY": -16.0,
    "CRS_ELAPSED_TIME": 305.0,
    "DISTANCE": 2486.0
  },
  {
    "FL_DATE": "2017-01-28T00:00:00",
    "ORIGIN": "OGG",
    "DEST": "LAX",
    "CRS_DEP_TIME": 2319,
    "CRS_ARR_TIME": 637,
    "ARR_DELAY": -23.0,
    "CRS_ELAPSED_TIME": 318.0,
    "DISTANCE": 2486.0
  },
  {
    "FL_DATE": "2017-01-28T00:00:00",
    "ORIGIN": "OGG",
    "DEST": "LAX",
    "CRS_DEP_TIME": 1413,
    "CRS_ARR_TIME": 2137,
    "ARR_DELAY": 7.0,
    "CRS_ELAPSED_TIME": 324.0,
    "DISTANCE": 2486.0
  },
  {
    "FL_DATE": "2017-01-28T00:00:00",
    "ORIGIN": "OGG",
    "DEST": "LAX",
    "CRS_DEP_TIME": 1347,
    "CRS_ARR_TIME": 2120,
    "ARR_DELAY": -19.0,
    "CRS_ELAPSED_TIME": 333.0,
    "DISTANCE": 2486.0
  },
  {
    "FL_DATE": "2017-01-28T00:00:00",
    "ORIGIN": "OGG",
    "DEST": "LAX",
    "CRS_DEP_TIME": 2310,
    "CRS_ARR_TIME": 639,
    "ARR_DELAY": -17.0,
    "CRS_ELAPSED_TIME": 329.0,
    "DISTANCE": 2486.0
  },
  {
    "FL_DATE": "2017-01-28T00:00:00",
    "ORIGIN": "OGG",
    "DEST": "LAX",
    "CRS_DEP_TIME": 1351,
    "CRS_ARR_TIME": 2118,
    "ARR_DELAY": -27.0,
    "CRS_ELAPSED_TIME": 327.0,
    "DISTANCE": 2486.0
  },
  {
    "FL_DATE": "2017-01-28T00:00:00",
    "ORIGIN": "OGG",
    "DEST": "LAX",
    "CRS_DEP_TIME": 2147,
    "CRS_ARR_TIME": 503,
    "ARR_DELAY": -16.0,
    "CRS_ELAPSED_TIME": 316.0,
    "DISTANCE": 2486.0
  },
  {
    "FL_DATE": "2017-01-28T00:00:00",
    "ORIGIN": "OGG",
    "DEST": "LAX",
    "CRS_DEP_TIME": 1440,
    "CRS_ARR_TIME": 2135,
    "ARR_DELAY": 36.0,
    "CRS_ELAPSED_TIME": 295.0,
    "DISTANCE": 2486.0
  },
  {
    "FL_DATE": "2017-01-29T00:00:00",
    "ORIGIN": "OGG",
    "DEST": "LAX",
    "CRS_DEP_TIME": 1351,
    "CRS_ARR_TIME": 2120,
    "ARR_DELAY": 115.0,
    "CRS_ELAPSED_TIME": 329.0,
    "DISTANCE": 2486.0
  },
  {
    "FL_DATE": "2017-01-29T00:00:00",
    "ORIGIN": "OGG",
    "DEST": "LAX",
    "CRS_DEP_TIME": 2142,
    "CRS_ARR_TIME": 500,
    "ARR_DELAY": -25.0,
    "CRS_ELAPSED_TIME": 318.0,
    "DISTANCE": 2486.0
  },
  {
    "FL_DATE": "2017-01-29T00:00:00",
    "ORIGIN": "OGG",
    "DEST": "LAX",
    "CRS_DEP_TIME": 1440,
    "CRS_ARR_TIME": 2135,
    "ARR_DELAY": -1.0,
    "CRS_ELAPSED_TIME": 295.0,
    "DISTANCE": 2486.0
  },
  {
    "FL_DATE": "2017-01-29T00:00:00",
    "ORIGIN": "OGG",
    "DEST": "LAX",
    "CRS_DEP_TIME": 1347,
    "CRS_ARR_TIME": 2120,
    "ARR_DELAY": -28.0,
    "CRS_ELAPSED_TIME": 333.0,
    "DISTANCE": 2486.0
  },
  {
    "FL_DATE": "2017-01-29T00:00:00",
    "ORIGIN": "OGG",
    "DEST": "LAX",
    "CRS_DEP_TIME": 2310,
    "CRS_ARR_TIME": 639,
    "ARR_DELAY": -20.0,
    "CRS_ELAPSED_TIME": 329.0,
    "DISTANCE": 2486.0
  },
  {
    "FL_DATE": "2017-01-29T00:00:00",
    "ORIGIN": "OGG",
    "DEST": "LAX",
    "CRS_DEP_TIME": 1530,
    "CRS_ARR_TIME": 2235,
    "ARR_DELAY": 0.0,
    "CRS_ELAPSED_TIME": 305.0,
    "DISTANCE": 2486.0
  },
  {
    "FL_DATE": "2017-01-29T00:00:00",
    "ORIGIN": "OGG",
    "DEST": "LAX",
    "CRS_DEP_TIME": 1413,
    "CRS_ARR_TIME": 2137,
    "ARR_DELAY": -26.0,
    "CRS_ELAPSED_TIME": 324.0,
    "DISTANCE": 2486.0
  },
  {
    "FL_DATE": "2017-01-30T00:00:00",
    "ORIGIN": "OGG",
    "DEST": "LAX",
    "CRS_DEP_TIME": 1351,
    "CRS_ARR_TIME": 2120,
    "ARR_DELAY": 26.0,
    "CRS_ELAPSED_TIME": 329.0,
    "DISTANCE": 2486.0
  },
  {
    "FL_DATE": "2017-01-30T00:00:00",
    "ORIGIN": "OGG",
    "DEST": "LAX",
    "CRS_DEP_TIME": 2142,
    "CRS_ARR_TIME": 500,
    "ARR_DELAY": -21.0,
    "CRS_ELAPSED_TIME": 318.0,
    "DISTANCE": 2486.0
  },
  {
    "FL_DATE": "2017-01-30T00:00:00",
    "ORIGIN": "OGG",
    "DEST": "LAX",
    "CRS_DEP_TIME": 1530,
    "CRS_ARR_TIME": 2235,
    "ARR_DELAY": -1.0,
    "CRS_ELAPSED_TIME": 305.0,
    "DISTANCE": 2486.0
  },
  {
    "FL_DATE": "2017-01-30T00:00:00",
    "ORIGIN": "OGG",
    "DEST": "LAX",
    "CRS_DEP_TIME": 1413,
    "CRS_ARR_TIME": 2137,
    "ARR_DELAY": 15.0,
    "CRS_ELAPSED_TIME": 324.0,
    "DISTANCE": 2486.0
  },
  {
    "FL_DATE": "2017-01-30T00:00:00",
    "ORIGIN": "OGG",
    "DEST": "LAX",
    "CRS_DEP_TIME": 1347,
    "CRS_ARR_TIME": 2120,
    "ARR_DELAY": -39.0,
    "CRS_ELAPSED_TIME": 333.0,
    "DISTANCE": 2486.0
  },
  {
    "FL_DATE": "2017-01-30T00:00:00",
    "ORIGIN": "OGG",
    "DEST": "LAX",
    "CRS_DEP_TIME": 2310,
    "CRS_ARR_TIME": 639,
    "ARR_DELAY": -38.0,
    "CRS_ELAPSED_TIME": 329.0,
    "DISTANCE": 2486.0
  },
  {
    "FL_DATE": "2017-01-30T00:00:00",
    "ORIGIN": "OGG",
    "DEST": "LAX",
    "CRS_DEP_TIME": 1440,
    "CRS_ARR_TIME": 2135,
    "ARR_DELAY": -7.0,
    "CRS_ELAPSED_TIME": 295.0,
    "DISTANCE": 2486.0
  },
  {
    "FL_DATE": "2017-01-31T00:00:00",
    "ORIGIN": "OGG",
    "DEST": "LAX",
    "CRS_DEP_TIME": 2142,
    "CRS_ARR_TIME": 500,
    "ARR_DELAY": -38.0,
    "CRS_ELAPSED_TIME": 318.0,
    "DISTANCE": 2486.0
  },
  {
    "FL_DATE": "2017-01-31T00:00:00",
    "ORIGIN": "OGG",
    "DEST": "LAX",
    "CRS_DEP_TIME": 1530,
    "CRS_ARR_TIME": 2235,
    "ARR_DELAY": -25.0,
    "CRS_ELAPSED_TIME": 305.0,
    "DISTANCE": 2486.0
  },
  {
    "FL_DATE": "2017-01-31T00:00:00",
    "ORIGIN": "OGG",
    "DEST": "LAX",
    "CRS_DEP_TIME": 1413,
    "CRS_ARR_TIME": 2137,
    "ARR_DELAY": -30.0,
    "CRS_ELAPSED_TIME": 324.0,
    "DISTANCE": 2486.0
  },
  {
    "FL_DATE": "2017-01-31T00:00:00",
    "ORIGIN": "OGG",
    "DEST": "LAX",
    "CRS_DEP_TIME": 1440,
    "CRS_ARR_TIME": 2135,
    "ARR_DELAY": 57.0,
    "CRS_ELAPSED_TIME": 295.0,
    "DISTANCE": 2486.0
  },
  {
    "FL_DATE": "2017-01-31T00:00:00",
    "ORIGIN": "OGG",
    "DEST": "LAX",
    "CRS_DEP_TIME": 1347,
    "CRS_ARR_TIME": 2120,
    "ARR_DELAY": -47.0,
    "CRS_ELAPSED_TIME": 333.0,
    "DISTANCE": 2486.0
  },
  {
    "FL_DATE": "2017-01-31T00:00:00",
    "ORIGIN": "OGG",
    "DEST": "LAX",
    "CRS_DEP_TIME": 2310,
    "CRS_ARR_TIME": 639,
    "ARR_DELAY": -35.0,
    "CRS_ELAPSED_TIME": 329.0,
    "DISTANCE": 2486.0
  }
]